mflux/__init__.py
mflux/callbacks/__init__.py
mflux/callbacks/callback.py
mflux/callbacks/callback_manager.py
mflux/callbacks/callback_registry.py
mflux/callbacks/callbacks.py
mflux/callbacks/generation_context.py
mflux/callbacks/instances/__init__.py
mflux/callbacks/instances/battery_saver.py
mflux/callbacks/instances/canny_saver.py
mflux/callbacks/instances/depth_saver.py
mflux/callbacks/instances/memory_saver.py
mflux/callbacks/instances/stepwise_handler.py
mflux/cli/__init__.py
mflux/cli/completions/README.md
mflux/cli/completions/__init__.py
mflux/cli/completions/generator.py
mflux/cli/completions/install.py
mflux/cli/defaults/__init__.py
mflux/cli/defaults/defaults.py
mflux/cli/parser/__init__.py
mflux/cli/parser/parsers.py
mflux/models/__init__.py
mflux/models/common/README.md
mflux/models/common/__init__.py
mflux/models/common/cli/__init__.py
mflux/models/common/cli/info.py
mflux/models/common/cli/lora_library.py
mflux/models/common/cli/save.py
mflux/models/common/cli/train.py
mflux/models/common/config/__init__.py
mflux/models/common/config/config.py
mflux/models/common/config/model_config.py
mflux/models/common/latent_creator/__init__.py
mflux/models/common/latent_creator/latent_creator.py
mflux/models/common/lora/__init__.py
mflux/models/common/lora/layer/__init__.py
mflux/models/common/lora/layer/fused_linear_lora_layer.py
mflux/models/common/lora/layer/linear_lora_layer.py
mflux/models/common/lora/mapping/__init__.py
mflux/models/common/lora/mapping/lora_loader.py
mflux/models/common/lora/mapping/lora_mapping.py
mflux/models/common/lora/mapping/lora_saver.py
mflux/models/common/lora/mapping/lora_transforms.py
mflux/models/common/resolution/__init__.py
mflux/models/common/resolution/actions.py
mflux/models/common/resolution/config_resolution.py
mflux/models/common/resolution/lora_resolution.py
mflux/models/common/resolution/path_resolution.py
mflux/models/common/resolution/quantization_resolution.py
mflux/models/common/schedulers/__init__.py
mflux-0.15.5.dist-info/WHEEL
mflux-0.15.5.dist-info/entry_points.txt
mflux-0.15.5.dist-info/METADATA
mflux-0.15.5.dist-info/RECORD
