Metadata-Version: 2.3
Name: mflux
Version: 0.15.5
Summary: A MLX port of FLUX based on the Huggingface Diffusers implementation.
Keywords: diffusers,flux,mlx
Author: Filip Strand
Author-email: Filip Strand <strand.filip@gmail.com>
License: MIT License
Classifier: Intended Audience :: Developers
Classifier: Operating System :: MacOS
Classifier: Operating System :: POSIX :: Linux
Classifier: Programming Language :: Python :: 3
Classifier: Programming Language :: Python :: 3.10
Classifier: Programming Language :: Python :: 3.11
Classifier: Programming Language :: Python :: 3.12
Classifier: Programming Language :: Python :: 3.13
Classifier: Programming Language :: Python :: 3.14
Requires-Dist: filelock>=3.20.1
Requires-Dist: fonttools>=4.60.2
Requires-Dist: huggingface-hub>=1.1.6,<2.0
Requires-Dist: matplotlib>=3.9.2,<4.0
Requires-Dist: mlx>=0.27.0,<0.31.0 ; sys_platform == 'darwin'
Requires-Dist: mlx[cuda13]>=0.30.3,<0.31.0 ; sys_platform == 'linux'
Requires-Dist: numpy>=2.0.1,<3.0
Requires-Dist: opencv-python>=4.10.0,<5.0
Requires-Dist: piexif>=1.1.3,<2.0
Requires-Dist: pillow>=10.4.0
Requires-Dist: pillow>=10.4.0,<11.0 ; python_full_version < '3.13'
Requires-Dist: pillow>=11.0,<12.0 ; python_full_version >= '3.13'
Requires-Dist: platformdirs>=4.0,<5.0
Requires-Dist: regex>=2024.11.6
Requires-Dist: requests>=2.32.4
Requires-Dist: safetensors>=0.4.4,<1.0
Requires-Dist: sentencepiece>=0.2.0,<1.0 ; python_full_version < '3.13'
Requires-Dist: sentencepiece>=0.2.1,<1.0 ; python_full_version >= '3.13'
Requires-Dist: tokenizers>=0.20.3 ; python_full_version >= '3.13'
Requires-Dist: toml>=0.10.2,<1.0
Requires-Dist: torch>=2.7.1
Requires-Dist: torch>=2.3.1,<3.0 ; python_full_version < '3.13'
Requires-Dist: torch>=2.8.0,<3.0 ; python_full_version >= '3.13'
Requires-Dist: tqdm>=4.66.5,<5.0
Requires-Dist: transformers>=5.0.0rc0,<6.0
Requires-Dist: twine>=6.1.0,<7.0
Requires-Dist: urllib3>=2.6.0
Requires-Dist: matplotlib>3.10,<4.0 ; extra == 'dev'
Requires-Dist: pytest>=8.3.0,<9.0 ; extra == 'dev'
Requires-Dist: pytest-timer>=1.0,<2.0 ; extra == 'dev'
Requires-Dist: mlx==0.30.3 ; sys_platform == 'darwin' and extra == 'dev'
Requires-Dist: mlx[cuda13]==0.30.3 ; sys_platform == 'linux' and extra == 'dev'
Maintainer: Filip Strand
Maintainer-email: Filip Strand <strand.filip@gmail.com>
Requires-Python: >=3.10
Project-URL: homepage, https://github.com/filipstrand/mflux
Provides-Extra: dev
